vuurvlieg/__init__.py
vuurvlieg/exceptions.py
vuurvlieg/firefly.py
vuurvlieg/models.py
vuurvlieg/py.typed
vuurvlieg-0.1.0.dist-info/LICENSE.md
vuurvlieg-0.1.0.dist-info/METADATA
vuurvlieg-0.1.0.dist-info/WHEEL
vuurvlieg-0.1.0.dist-info/RECORD
